AiraTranslation/__init__.py
AiraTranslation/service.py
AiraTranslation-0.1.0.dist-info/LICENSE
AiraTranslation-0.1.0.dist-info/METADATA
AiraTranslation-0.1.0.dist-info/WHEEL
AiraTranslation-0.1.0.dist-info/top_level.txt
AiraTranslation-0.1.0.dist-info/RECORD
