Metadata-Version: 2.1
Name: AiraTranslation
Version: 0.1.0
Summary: A example Python package
Home-page: UNKNOWN
Author: Badal Singh
Author-email: Badal.Singh@evalueserve.com
License: UNKNOWN
Platform: UNKNOWN
Classifier: Development Status :: 1 - Planning
Classifier: Intended Audience :: Science/Research
Classifier: License :: OSI Approved :: MIT License
Classifier: Operating System :: OS Independent
Classifier: Programming Language :: Python :: 3.6
